qdrant_loader/__init__.py
qdrant_loader/config.py
qdrant_loader/main.py
qdrant_loader/cli/__init__.py
qdrant_loader/cli/async_utils.py
qdrant_loader/cli/asyncio.py
qdrant_loader/cli/cli.py
qdrant_loader/cli/config_loader.py
qdrant_loader/cli/logging_utils.py
qdrant_loader/cli/path_utils.py
qdrant_loader/cli/project_commands.py
qdrant_loader/cli/update_check.py
qdrant_loader/cli/version.py
qdrant_loader/cli/commands/__init__.py
qdrant_loader/cli/commands/config.py
qdrant_loader/cli/commands/config_cmd.py
qdrant_loader/cli/commands/ingest.py
qdrant_loader/cli/commands/ingest_cmd.py
qdrant_loader/cli/commands/init.py
qdrant_loader/cli/commands/init_cmd.py
qdrant_loader/cli/commands/project/__init__.py
qdrant_loader/cli/commands/project/list_cmd.py
qdrant_loader/cli/commands/project/status_cmd.py
qdrant_loader/cli/commands/project/validate_cmd.py
qdrant_loader/config/__init__.py
qdrant_loader/config/base.py
qdrant_loader/config/chunking.py
qdrant_loader/config/embedding.py
qdrant_loader/config/global_config.py
qdrant_loader/config/models.py
qdrant_loader/config/parser.py
qdrant_loader/config/qdrant.py
qdrant_loader/config/source_config.py
qdrant_loader/config/sources.py
qdrant_loader/config/state.py
qdrant_loader/config/types.py
qdrant_loader/config/validator.py
qdrant_loader/config/workspace.py
qdrant_loader/connectors/__init__.py
qdrant_loader/connectors/attachments.py
qdrant_loader/connectors/base.py
qdrant_loader/connectors/exceptions.py
qdrant_loader/connectors/http.py
qdrant_loader/connectors/confluence/__init__.py
qdrant_loader/connectors/confluence/auth.py
qdrant_loader/connectors/confluence/config.py
qdrant_loader/connectors/confluence/connector.py
qdrant_loader/connectors/confluence/mappers.py
qdrant_loader/connectors/confluence/pagination.py
qdrant_loader/connectors/git/__init__.py
qdrant_loader/connectors/git/adapter.py
qdrant_loader/connectors/git/config.py
qdrant_loader/connectors/git/connector.py
qdrant_loader/connectors/git/file_processor.py
qdrant_loader-0.7.6.dist-info/METADATA
qdrant_loader-0.7.6.dist-info/WHEEL
qdrant_loader-0.7.6.dist-info/entry_points.txt
qdrant_loader-0.7.6.dist-info/top_level.txt
qdrant_loader-0.7.6.dist-info/RECORD
