Metadata-Version: 2.4
Name: qdrant-loader
Version: 0.7.6
Summary: A tool for collecting and vectorizing technical content from multiple sources and storing it in a QDrant vector database.
Author-email: Martin Papy <martin.papy@cbtw.tech>
License-Expression: GPL-3.0
Project-URL: Homepage, https://qdrant-loader.net
Project-URL: Documentation, https://qdrant-loader.net/docs/packages/qdrant-loader/README.html
Project-URL: Repository, https://github.com/martin-papy/qdrant-loader
Project-URL: Issues, https://github.com/martin-papy/qdrant-loader/issues
Keywords: qdrant,vector-database,embeddings,document-processing,multi-project,rag,semantic-search
Classifier: Development Status :: 5 - Production/Stable
Classifier: Intended Audience :: Developers
Classifier: Intended Audience :: Information Technology
Classifier: Intended Audience :: Science/Research
Classifier: Operating System :: OS Independent
Classifier: Programming Language :: Python :: 3
Classifier: Programming Language :: Python :: 3.12
Classifier: Topic :: Database
Classifier: Topic :: Database :: Database Engines/Servers
Classifier: Topic :: Scientific/Engineering :: Artificial Intelligence
Classifier: Topic :: Scientific/Engineering :: Information Analysis
Classifier: Topic :: Software Development :: Libraries :: Python Modules
Classifier: Topic :: Text Processing :: Indexing
Classifier: Topic :: Text Processing :: Linguistic
Classifier: Environment :: Console
Classifier: Typing :: Typed
Requires-Python: >=3.12
Requires-Dist: click>=8.1.7
Requires-Dist: requests>=2.31.0
Requires-Dist: tomli>=2.0.1
Requires-Dist: tomli-w>=1.0.0
Requires-Dist: python-dotenv>=1.0.0
Requires-Dist: pydantic>=2.0.0
Requires-Dist: pydantic-settings>=2.0.0
Requires-Dist: structlog>=23.0.0
Requires-Dist: httpx>=0.24.0
Requires-Dist: openai>=1.0.0
Requires-Dist: qdrant-loader-core[openai]==0.7.6
Requires-Dist: qdrant-client>=1.7.0
Requires-Dist: PyYAML>=6.0.0
Requires-Dist: beautifulsoup4>=4.12.0
Requires-Dist: chardet>=5.2.0
Requires-Dist: tiktoken>=0.5.0
Requires-Dist: langchain>=0.3.0
Requires-Dist: langchain-core>=0.3.0
Requires-Dist: langchain-community>=0.0.38
Requires-Dist: langchain-text-splitters>=0.3.9
Requires-Dist: numpy<2.0.0,>=1.26.0
Requires-Dist: GitPython>=3.1.40
Requires-Dist: atlassian-python-api>=3.41.0
Requires-Dist: tqdm>=4.66.0
Requires-Dist: SQLAlchemy>=2.0.0
Requires-Dist: alembic>=1.12.0
Requires-Dist: appdirs>=1.4.4
Requires-Dist: aiosqlite>=0.19.0
Requires-Dist: greenlet>=3.0.0
Requires-Dist: spacy>=3.7.0
Requires-Dist: nltk>=3.8.0
Requires-Dist: gensim>=4.3.0
Requires-Dist: rank-bm25>=0.2.2
Requires-Dist: faiss-cpu>=1.7.4
Requires-Dist: psutil>=5.9.0
Requires-Dist: tree-sitter-languages>=1.10.0
Requires-Dist: tree-sitter<0.21
Requires-Dist: markitdown[all]>=0.1.3
Requires-Dist: rich>=13.0.0
Requires-Dist: packaging>=21.0
Requires-Dist: prometheus-client<1.0.0,>=0.19.0
